pdir/__init__.py
pdir/_internal_utils.py
pdir/api.py
pdir/attr_category.py
pdir/color.py
pdir/configuration.py
pdir/constants.py
pdir/format.py
pdir2-1.1.1.dist-info/WHEEL
pdir2-1.1.1.dist-info/METADATA
pdir2-1.1.1.dist-info/licenses/LICENSE
pdir2-1.1.1.dist-info/RECORD
