Metadata-Version: 2.1
Name: pdir2
Version: 1.1.1
Summary: Pretty dir printing with joy
License: MIT
Author-email: laike9m <laike9m@gmail.com>
Requires-Python: >=3.8
Classifier: Intended Audience :: Developers
Classifier: License :: OSI Approved :: MIT License
Classifier: Operating System :: MacOS :: MacOS X
Classifier: Operating System :: Microsoft :: Windows
Classifier: Operating System :: POSIX
Classifier: Programming Language :: Python
Classifier: Programming Language :: Python :: 3
Classifier: Programming Language :: Python :: 3.10
Classifier: Programming Language :: Python :: 3.11
Classifier: Programming Language :: Python :: 3.12
Classifier: Programming Language :: Python :: 3.13
Classifier: Programming Language :: Python :: 3.8
Classifier: Programming Language :: Python :: 3.9
Classifier: Programming Language :: Python :: Implementation :: CPython
Classifier: Programming Language :: Python :: Implementation :: PyPy
Classifier: Topic :: Software Development :: Libraries :: Python Modules
Requires-Dist: colorama; platform_system == "Windows"
Requires-Dist: typing-extensions==4.*
Project-URL: Bug Tracker, https://github.com/laike9m/pdir2/issues
Project-URL: Funding, https://github.com/sponsors/laike9m
Project-URL: homepage, https://github.com/laike9m/pdir2
Project-URL: repository, https://github.com/laike9m/pdir2
